demo.py
check_connection/__init__.py
check_connection/check_connection.py
check_connection-0.0.3.dist-info/LICENSE.txt
check_connection-0.0.3.dist-info/METADATA
check_connection-0.0.3.dist-info/WHEEL
check_connection-0.0.3.dist-info/top_level.txt
check_connection-0.0.3.dist-info/RECORD
