Metadata-Version: 2.1
Name: check-connection
Version: 0.0.3
Summary: Function to check connection to certain server
Author: Raphael Trinkler
Author-email: raphael.trinkler@infineon.com
Maintainer-email: Raphael Trinkler <raphael.trinkler@infineon.com>
License: Proprietary.
Project-URL: Bitbucket, https://bitbucket.vih.infineon.com/projects/SCSS/repos/py-template-project/browse?at=refs%2Fheads%2Ffeature
Keywords: connection,check,template
Classifier: Programming Language :: Python :: 3
Classifier: Programming Language :: Python :: 3
Requires-Python: >=3.7
License-File: LICENSE.txt
Requires-Dist: flake8
Requires-Dist: pdoc3
Requires-Dist: pytest
Requires-Dist: requests
Requires-Dist: PySimpleGUI
